GitCommunityBookZhongwenban/README.md
GitCommunityBookZhongwenban/__init__.py
GitCommunityBookZhongwenban/__main__.py
GitCommunityBookZhongwenban/file.epub
GitCommunityBookZhongwenban/index.html
GitCommunityBookZhongwenban/css/__init__.py
GitCommunityBookZhongwenban/css/annotations.css
GitCommunityBookZhongwenban/css/main.css
GitCommunityBookZhongwenban/css/normalize.css
GitCommunityBookZhongwenban/css/popup.css
GitCommunityBookZhongwenban/font/__init__.py
GitCommunityBookZhongwenban/font/fontello.eot
GitCommunityBookZhongwenban/font/fontello.svg
GitCommunityBookZhongwenban/font/fontello.ttf
GitCommunityBookZhongwenban/font/fontello.woff
GitCommunityBookZhongwenban/img/__init__.py
GitCommunityBookZhongwenban/img/annotator-glyph-sprite.png
GitCommunityBookZhongwenban/img/annotator-icon-sprite.png
GitCommunityBookZhongwenban/img/apple-touch-icon.png
GitCommunityBookZhongwenban/img/cancelfullscreen.png
GitCommunityBookZhongwenban/img/close.png
GitCommunityBookZhongwenban/img/fullscreen.png
GitCommunityBookZhongwenban/img/loader.gif
GitCommunityBookZhongwenban/img/menu-icon.png
GitCommunityBookZhongwenban/img/save.png
GitCommunityBookZhongwenban/img/saved.png
GitCommunityBookZhongwenban/img/settings-s.png
GitCommunityBookZhongwenban/img/settings.png
GitCommunityBookZhongwenban/img/star.png
GitCommunityBookZhongwenban/js/__init__.py
GitCommunityBookZhongwenban/js/epub.js
GitCommunityBookZhongwenban/js/epub.min.js
GitCommunityBookZhongwenban/js/epub.min.map
GitCommunityBookZhongwenban/js/hooks.min.js
GitCommunityBookZhongwenban/js/hooks.min.map
GitCommunityBookZhongwenban/js/reader.js
GitCommunityBookZhongwenban/js/reader.js.map
GitCommunityBookZhongwenban/js/reader.min.js
GitCommunityBookZhongwenban/js/reader.min.map
GitCommunityBookZhongwenban/js/hooks/__init__.py
GitCommunityBookZhongwenban/js/hooks/extensions/__init__.py
GitCommunityBookZhongwenban/js/hooks/extensions/highlight.js
GitCommunityBookZhongwenban/js/libs/__init__.py
git_community_book_zhongwenban-2024.3.2.0.dist-info/METADATA
git_community_book_zhongwenban-2024.3.2.0.dist-info/WHEEL
git_community_book_zhongwenban-2024.3.2.0.dist-info/entry_points.txt
git_community_book_zhongwenban-2024.3.2.0.dist-info/top_level.txt
git_community_book_zhongwenban-2024.3.2.0.dist-info/RECORD
